Workbook

Sheet Cover
A1: TCS FY2026 Business Analysis
A2: Professional workbook covering performance, transformation, risks and decision support
A4: CONTENTS
A6: Dashboard | B6: Executive KPIs, industry, geography, priorities and AI summary.
A7: 01_MASTER_ALL_DATA | B7: Consolidated source metrics used throughout the workbook.
A8: 02_FINANCIAL_ANALYSIS | B8: Headline revenue, profit, margin and growth interpretation.
A9: 03_INDUSTRY_ANALYSIS | B9: Vertical revenue, growth, share and margin analysis.
A10: 04_GEOGRAPHY_ANALYSIS | B10: Revenue mix, ranking and concentration by geography.
A11: 05_AI_ANALYSIS | B11: AI monetisation, talent, learning and capability indicators.
A12: 06_MANAGEMENT_PRIORITIES | B12: Ranked issues and recommended management analysis.
A13: 07_15_BUSINESS_INSIGHTS | B13: Fifteen evidence-based findings and analyst actions.
A14: 08_RECRUITER_PROJECT_STORY | B14: End-to-end business analytics project narrative.
A15: 09_SQL_QUESTIONS | B15: Twenty SQL interview questions based on the dataset.
A16: 10_DASHBOARD_LAYOUT | B16: Blueprint for a multi-page reporting solution.
A17: 11_METHODOLOGY | B17: Source, scope, period and calculation methodology.

Sheet Dashboard
A1: TCS FY2026 Executive Dashboard | N1: Industry | O1: FY2026 | P1: FY2025 | R1: Geography | S1: Revenue Mix
A2: Financial performance, industry dynamics, geographic concentration and AI transformation | N2: ='03_INDUSTRY_ANALYSIS'!A5 -> BFSI | O2: ='03_INDUSTRY_ANALYSIS'!B5 -> 103363 | P2: ='03_INDUSTRY_ANALYSIS'!C5 -> 94597 | R2: ='04_GEOGRAPHY_ANALYSIS'!A5 -> North America | S2: ='04_GEOGRAPHY_ANALYSIS'!B5 -> 48.6
N3: ='03_INDUSTRY_ANALYSIS'!A6 -> Consumer Business | O3: ='03_INDUSTRY_ANALYSIS'!B6 -> 42432 | P3: ='03_INDUSTRY_ANALYSIS'!C6 -> 40197 | R3: ='04_GEOGRAPHY_ANALYSIS'!A6 -> United Kingdom | S3: ='04_GEOGRAPHY_ANALYSIS'!B6 -> 17.4
A4: REVENUE | D4: EBIT | G4: PAT | J4: EPS | N4: ='03_INDUSTRY_ANALYSIS'!A7 -> Communication, Media and Technology | O4: ='03_INDUSTRY_ANALYSIS'!B7 -> 39474 | P4: ='03_INDUSTRY_ANALYSIS'!C7 -> 45893 | R4: ='04_GEOGRAPHY_ANALYSIS'!A7 -> Continental Europe | S4: ='04_GEOGRAPHY_ANALYSIS'!B7 -> 15.4
B5: ='01_MASTER_ALL_DATA'!E5 -> 267021 | E5: ='01_MASTER_ALL_DATA'!E6 -> 66838 | H5: ='01_MASTER_ALL_DATA'!E7 -> 52820 | K5: ='01_MASTER_ALL_DATA'!E8 -> 145.99 | N5: ='03_INDUSTRY_ANALYSIS'!A8 -> Life Sciences and Healthcare | O5: ='03_INDUSTRY_ANALYSIS'!B8 -> 27745 | P5: ='03_INDUSTRY_ANALYSIS'!C8 -> 26456 | R5: ='04_GEOGRAPHY_ANALYSIS'!A8 -> APAC | S5: ='04_GEOGRAPHY_ANALYSIS'!B8 -> 8.3
N6: ='03_INDUSTRY_ANALYSIS'!A9 -> Manufacturing | O6: ='03_INDUSTRY_ANALYSIS'!B9 -> 26614 | P6: ='03_INDUSTRY_ANALYSIS'!C9 -> 25170 | R6: ='04_GEOGRAPHY_ANALYSIS'!A9 -> India | S6: ='04_GEOGRAPHY_ANALYSIS'!B9 -> 5.9
A7: ='01_MASTER_ALL_DATA'!H5/100 -> 0.046 | D7: ='01_MASTER_ALL_DATA'!H6/100 -> 0.075 | G7: ='01_MASTER_ALL_DATA'!H7/100 -> 0.088 | J7: ='01_MASTER_ALL_DATA'!H8/100 -> 0.088 | N7: ='03_INDUSTRY_ANALYSIS'!A10 -> Others | O7: ='03_INDUSTRY_ANALYSIS'!B10 -> 27393 | P7: ='03_INDUSTRY_ANALYSIS'!C10 -> 23011 | R7: ='04_GEOGRAPHY_ANALYSIS'!A10 -> Latin America | S7: ='04_GEOGRAPHY_ANALYSIS'!B10 -> 1.9
R8: ='04_GEOGRAPHY_ANALYSIS'!A11 -> MEA | S8: ='04_GEOGRAPHY_ANALYSIS'!B11 -> 2.5
A9: STORY IN BRIEF
A10: TCS delivered positive FY2026 growth with revenue up 4.6%, while EBIT and PAT grew faster at 7.5% and 8.8%. BFSI remains the core revenue engine, but CMT contracted 14.0% even as its margin improved sharply. North America contributes 48.6% of revenue mix, creating concentration to monitor, while US$2.3B in annualised AI services revenue and 270,000 AI-proficient employees show meaningful transformation scale.
A13: INDUSTRY REVENUE | H13: GEOGRAPHIC MIX
A31: 01 MANAGEMENT PRIORITY MATRIX | H31: 02 AI TRANSFORMATION SCORECARD
A32: RANK | B32: FOCUS AREA | D32: WHY IT MATTERS | F32: LEVEL | H32: CAPABILITY METRIC | K32: FY2026 SCALE
A33: ='06_MANAGEMENT_PRIORITIES'!A5 -> 1 | B33: ='06_MANAGEMENT_PRIORITIES'!B5 -> CMT | D33: ='06_MANAGEMENT_PRIORITIES'!C5 -> Revenue declined 14.0% | F33: ='06_MANAGEMENT_PRIORITIES'!D5 -> High | H33: Annualised AI services revenue | K33: ='05_AI_ANALYSIS'!B5 -> US$2.3B
A34: ='06_MANAGEMENT_PRIORITIES'!A6 -> 2 | B34: ='06_MANAGEMENT_PRIORITIES'!B6 -> BFSI | D34: ='06_MANAGEMENT_PRIORITIES'!C6 -> Largest revenue pool: ₹103,363 Cr | F34: ='06_MANAGEMENT_PRIORITIES'!D6 -> High | H34: New-age services revenue | K34: ='05_AI_ANALYSIS'!B6 -> US$11.5B
A35: ='06_MANAGEMENT_PRIORITIES'!A7 -> 3 | B35: ='06_MANAGEMENT_PRIORITIES'!B7 -> North America | D35: ='06_MANAGEMENT_PRIORITIES'!C7 -> 48.6% revenue mix | F35: ='06_MANAGEMENT_PRIORITIES'!D7 -> High | H35: AI/ML proficient employees | K35: ='05_AI_ANALYSIS'!B7 -> 270000
A36: ='06_MANAGEMENT_PRIORITIES'!A8 -> 4 | B36: ='06_MANAGEMENT_PRIORITIES'!B8 -> AI Services | D36: ='06_MANAGEMENT_PRIORITIES'!C8 -> US$2.3B annualised revenue | F36: ='06_MANAGEMENT_PRIORITIES'!D8 -> High | H36: Learning hours | K36: ='05_AI_ANALYSIS'!B8 -> 69
A37: ='06_MANAGEMENT_PRIORITIES'!A9 -> 5 | B37: ='06_MANAGEMENT_PRIORITIES'!B9 -> Manufacturing | D37: ='06_MANAGEMENT_PRIORITIES'!C9 -> 30.3% segment margin | F37: ='06_MANAGEMENT_PRIORITIES'!D9 -> Medium | H37: Competencies acquired | K37: ='05_AI_ANALYSIS'!B9 -> 5.2

Sheet 01_MASTER_ALL_DATA
A1: TCS FY2026 Master Data
A2: Consolidated financial, industry, geography and AI metrics from the annual report.
A4: Analysis_Domain | B4: Data_Table | C4: Dimension | D4: Metric | E4: FY2026_Value | F4: Unit | G4: FY2025_Value | H4: YoY_or_Change | I4: Source
A5: Financial Performance | B5: Financials | C5: Revenue from operations | D5: FY2026 | E5: 267021 | F5: ₹ crore | G5: 255324 | H5: 4.6 | I5: TCS FY2026 Annual Report
A6: Financial Performance | B6: Financials | C6: EBIT before other income | D6: FY2026 | E6: 66838 | F6: ₹ crore | G6: 62165 | H6: 7.5 | I6: TCS FY2026 Annual Report
A7: Financial Performance | B7: Financials | C7: PAT attributable to shareholders | D7: FY2026 | E7: 52820 | F7: ₹ crore | G7: 48553 | H7: 8.8 | I7: TCS FY2026 Annual Report
A8: Financial Performance | B8: Financials | C8: EPS | D8: FY2026 | E8: 145.99 | F8: ₹ per share | G8: 134.19 | H8: 8.8 | I8: TCS FY2026 Annual Report
A9: Financial Performance | B9: Financials | C9: EBIT margin | D9: FY2026 | E9: 25 | F9: % | G9: 24.3 | H9: 0.7 | I9: TCS FY2026 Annual Report
A10: Financial Performance | B10: Financials | C10: Net margin | D10: FY2026 | E10: 19.8 | F10: % | G10: 19 | H10: 0.8 | I10: TCS FY2026 Annual Report
A11: Industry Performance | B11: Industry | C11: BFSI | D11: FY2026 Revenue | E11: 103363 | F11: ₹ crore | G11: 94597 | H11: 9.3 | I11: TCS FY2026 Annual Report
A12: Industry Performance | B12: Industry | C12: BFSI | D12: FY2026 Margin | E12: 26.1 | F12: % | G12: 26.6 | H12: -0.5 | I12: TCS FY2026 Annual Report
A13: Industry Performance | B13: Industry | C13: Consumer Business | D13: FY2026 Revenue | E13: 42432 | F13: ₹ crore | G13: 40197 | H13: 5.6 | I13: TCS FY2026 Annual Report
A14: Industry Performance | B14: Industry | C14: Consumer Business | D14: FY2026 Margin | E14: 28.5 | F14: % | G14: 27.9 | H14: 0.6 | I14: TCS FY2026 Annual Report
A15: Industry Performance | B15: Industry | C15: Communication, Media and Technology | D15: FY2026 Revenue | E15: 39474 | F15: ₹ crore | G15: 45893 | H15: -14 | I15: TCS FY2026 Annual Report
A16: Industry Performance | B16: Industry | C16: Communication, Media and Technology | D16: FY2026 Margin | E16: 29.1 | F16: % | G16: 20.9 | H16: 8.2 | I16: TCS FY2026 Annual Report
... A22: Industry Performance | B22: Industry | C22: Others | D22: FY2026 Margin | E22: 22.9 | F22: % | G22: 25.2 | H22: -2.3 | I22: TCS FY2026 Annual Report
A23: Geography | B23: Geography | C23: North America | D23: Revenue Mix | E23: 48.6 | F23: % | I23: TCS FY2026 Annual Report
A24: Geography | B24: Geography | C24: United Kingdom | D24: Revenue Mix | E24: 17.4 | F24: % | I24: TCS FY2026 Annual Report
A25: Geography | B25: Geography | C25: Continental Europe | D25: Revenue Mix | E25: 15.4 | F25: % | I25: TCS FY2026 Annual Report
A26: Geography | B26: Geography | C26: APAC | D26: Revenue Mix | E26: 8.3 | F26: % | I26: TCS FY2026 Annual Report
A27: Geography | B27: Geography | C27: India | D27: Revenue Mix | E27: 5.9 | F27: % | I27: TCS FY2026 Annual Report
A28: Geography | B28: Geography | C28: Latin America | D28: Revenue Mix | E28: 1.9 | F28: % | I28: TCS FY2026 Annual Report
A29: Geography | B29: Geography | C29: MEA | D29: Revenue Mix | E29: 2.5 | F29: % | I29: TCS FY2026 Annual Report
A30: AI Transformation | B30: AI | C30: Annualised AI Services revenue | D30: FY2026 | E30: US$2.3B | F30: AI transformation | I30: TCS FY2026 Annual Report
A31: AI Transformation | B31: AI | C31: New-age services revenue | D31: FY2026 | E31: US$11.5B | F31: FY2026 | I31: TCS FY2026 Annual Report
A32: AI Transformation | B32: AI | C32: Higher-order AI/ML proficiency | D32: FY2026 | E32: 270000 | F32: people | I32: TCS FY2026 Annual Report
A33: AI Transformation | B33: AI | C33: Learning hours | D33: FY2026 | E33: 69 | F33: million hours | I33: TCS FY2026 Annual Report
A34: AI Transformation | B34: AI | C34: Competencies acquired | D34: FY2026 | E34: 5.2 | F34: million | I34: TCS FY2026 Annual Report
A35: AI Transformation | B35: AI | C35: AI hackathon participants | D35: FY2026 | E35: 281000 | F35: participants | I35: TCS FY2026 Annual Report

Sheet 02_FINANCIAL_ANALYSIS
A1: Financial Performance
A2: Headline FY2026 financial results, comparisons and management interpretation.
A4: KPI | B4: FY2026 | C4: Comparison | D4: Finding | E4: Next Analysis
A5: Revenue | B5: ₹267,021 Cr | C5: 4.6% YoY | D5: Positive growth | E5: Analyze industry/geography drivers
A6: EBIT | B6: ₹66,838 Cr | C6: 7.5% YoY | D6: EBIT grew faster than revenue | E6: Investigate margin resilience
A7: PAT | B7: ₹52,820 Cr | C7: 8.8% YoY | D7: PAT grew faster than revenue | E7: Monitor sustainability
A8: EBIT Margin | B8: 25.0% | C8: 24.3% FY2025 | D8: Improved | E8: Compare segment margins
A9: Net Margin | B9: 19.8% | C9: 19.0% FY2025 | D9: Improved | E9: Track future trend

Sheet 03_INDUSTRY_ANALYSIS
A1: Industry Performance
A2: Revenue, growth, margin and share comparison across six industry verticals.
A4: Industry | B4: FY2026_Revenue_₹Cr | C4: FY2025_Revenue_₹Cr | D4: YoY_Growth_% | E4: FY2026_Margin_% | F4: FY2025_Margin_% | G4: Revenue_Share_% | H4: Growth_Flag | I4: Margin_Change_pp
A5: BFSI | B5: 103363 | C5: 94597 | D5: 9.3 | E5: 26.1 | F5: 26.6 | G5: 38.7 | H5: Healthy | I5: -0.5
A6: Consumer Business | B6: 42432 | C6: 40197 | D6: 5.6 | E6: 28.5 | F6: 27.9 | G6: 15.9 | H6: Healthy | I6: 0.6
A7: Communication, Media and Technology | B7: 39474 | C7: 45893 | D7: -14 | E7: 29.1 | F7: 20.9 | G7: 14.8 | H7: Decline | I7: 8.2
A8: Life Sciences and Healthcare | B8: 27745 | C8: 26456 | D8: 4.9 | E8: 27 | F8: 28.2 | G8: 10.4 | H8: Low Growth | I8: -1.2
A9: Manufacturing | B9: 26614 | C9: 25170 | D9: 5.7 | E9: 30.3 | F9: 32.7 | G9: 10 | H9: Healthy | I9: -2.4
A10: Others | B10: 27393 | C10: 23011 | D10: 19 | E10: 22.9 | F10: 25.2 | G10: 10.3 | H10: High Growth | I10: -2.3

Sheet 04_GEOGRAPHY_ANALYSIS
A1: Geographic Mix
A2: FY2026 revenue concentration and ranking across seven reported geographies.
A4: Geography | B4: Revenue_Mix_% | C4: Rank | D4: Top_3
A5: North America | B5: 48.6 | C5: 1 | D5: TRUE
A6: United Kingdom | B6: 17.4 | C6: 2 | D6: TRUE
A7: Continental Europe | B7: 15.4 | C7: 3 | D7: TRUE
A8: APAC | B8: 8.3 | C8: 4 | D8: FALSE
A9: India | B9: 5.9 | C9: 5 | D9: FALSE
A10: Latin America | B10: 1.9 | C10: 7 | D10: FALSE
A11: MEA | B11: 2.5 | C11: 6 | D11: FALSE

Sheet 05_AI_ANALYSIS
A1: AI Transformation
A2: Commercial scale, workforce capability and learning indicators for FY2026.
A4: Metric | B4: FY2026_Value | C4: Unit_or_Context | D4: Recruiter_Relevance
A5: Annualised AI Services revenue | B5: US$2.3B | C5: AI transformation | D5: Strategic growth KPI
A6: New-age services revenue | B6: US$11.5B | C6: FY2026 | D6: New-age services scale
A7: Higher-order AI/ML proficiency | B7: 270000 | C7: people | D7: AI workforce capability
A8: Learning hours | B8: 69 | C8: million hours | D8: Reskilling investment
A9: Competencies acquired | B9: 5.2 | C9: million | D9: Capability building
A10: AI hackathon participants | B10: 281000 | C10: participants | D10: AI ecosystem participation

Sheet 06_MANAGEMENT_PRIORITIES
A1: Management Priorities
A2: Decision-focused issues ranked by urgency, evidence and recommended analysis.
A4: Priority | B4: Area | C4: Evidence | D4: Priority_Level | E4: Recommended_Analysis
A5: 1 | B5: CMT | C5: Revenue declined 14.0% | D5: High | E5: Deep-dive demand, portfolio mix and account performance
A6: 2 | B6: BFSI | C6: Largest revenue pool: ₹103,363 Cr | D6: High | E6: Protect core and expand AI-led services
A7: 3 | B7: North America | C7: 48.6% revenue mix | D7: High | E7: Monitor geographic concentration
A8: 4 | B8: AI Services | C8: US$2.3B annualised revenue | D8: High | E8: Track monetisation against AI capability
A9: 5 | B9: Manufacturing | C9: 30.3% segment margin | D9: Medium | E9: Benchmark operating practices

Sheet 07_15_BUSINESS_INSIGHTS
A1: 15 Business Insights
A2: Evidence, interpretation and analyst actions distilled from the FY2026 report.
A4: # | B4: Theme | C4: What the report shows | D4: Analytical interpretation | E4: Analyst action
A5: 1 | B5: Overall growth | C5: Revenue reached ₹267,021 Cr, up 4.6% YoY. | D5: Growth remained positive but was slower than the prior-year reported 6.0% pace. | E5: Monitor growth recovery by industry and geography.
A6: 2 | B6: Profitability | C6: EBIT reached ₹66,838 Cr and EBIT margin was 25.0%. | D6: EBIT grew faster than revenue (7.5% vs 4.6%). | E6: Investigate the operating levers behind margin resilience.
A7: 3 | B7: Net profitability | C7: PAT was ₹52,820 Cr with 19.8% net margin. | D7: PAT growth was 8.8%, ahead of revenue growth. | E7: Track whether margin expansion remains sustainable.
A8: 4 | B8: Largest industry | C8: BFSI generated ₹103,363 Cr, the largest industry revenue pool. | D8: It represented about 38.7% of reported revenue mix. | E8: BFSI remains a major concentration and growth driver.
A9: 5 | B9: Fastest listed industry growth | C9: Others grew 19.0% YoY. | D9: It was the highest growth rate among the listed industry verticals. | E9: Identify which businesses sit inside Others and their growth drivers.
A10: 6 | B10: Industry pressure | C10: Communication, Media and Technology revenue fell 14.0%. | D10: It was the only listed industry with negative YoY growth. | E10: This is a priority area for diagnostic analysis.
A11: 7 | B11: CMT margin | C11: CMT margin increased to 29.1% from 20.9%. | D11: Margin improved despite revenue contraction. | E11: Study mix, productivity and cost factors before drawing conclusions.
A12: 8 | B12: Manufacturing profitability | C12: Manufacturing margin was 30.3%. | D12: It was the highest FY2026 segment margin among the listed verticals. | E12: Compare its operating model with lower-margin verticals.
A13: 9 | B13: Largest geography | C13: North America accounted for 48.6% of revenue mix. | D13: It is the largest geographic revenue pool. | E13: Geographic concentration is important for portfolio risk analysis.
A14: 10 | B14: Second geography | C14: UK represented 17.4% of revenue mix. | D14: UK was the second-largest listed geography. | E14: Track regional growth and demand signals separately.
A15: 11 | B15: AI monetisation | C15: Annualised AI Services revenue reached US$2.3B. | D15: The report links this to the AI-led transformation strategy. | E15: Use AI revenue as a strategic KPI rather than only a technology metric.
A16: 12 | B16: AI talent | C16: 270,000 employees had higher-order AI/ML proficiency. | D16: The report highlights reskilling and AI capability building. | E16: Compare talent capability with AI revenue growth in future periods.
... A19: 15 | B19: Infrastructure strategy | C19: TCS launched HyperVault and discussed AI infrastructure expansion in India. | D19: The report describes an initial 1GW data-centre capacity plan and a 100MW initial OpenAI partnership phase. | E19: Infrastructure is positioned as part of the broader Infrastructure-to-Intelligence strategy.

Sheet 08_RECRUITER_PROJECT_STORY
A1: Recruiter Project Story
A2: A concise analytical storyline from business question to decision support.
A4: Stage | B4: Business Question | C4: Data Used
A5: Problem | B5: How did TCS perform in FY2026? | C5: Financial KPIs
A6: Segmentation | B6: Which industries and geographies drove the business? | C6: Industry + Geography
A7: Diagnosis | B7: Where are the strongest and weakest signals? | C7: Growth + Margin
A8: Transformation | B8: How significant is AI? | C8: AI metrics
A9: Decision Support | B9: What should management investigate next? | C9: Priority analysis

Sheet 09_SQL_QUESTIONS
A1: SQL Interview Questions
A2: Twenty practical questions based on the TCS FY2026 analytical dataset.
A4: SQL_Interview_Questions
A5: 1. Return FY2026 revenue, EBIT, PAT and EPS.
A6: 2. Calculate revenue YoY growth from FY2025 to FY2026.
A7: 3. Rank industry verticals by FY2026 revenue.
A8: 4. Rank industries by YoY growth.
A9: 5. Find industries with negative YoY growth.
A10: 6. Find the highest FY2026 segment margin.
A11: 7. Calculate each industry's share of total FY2026 revenue.
A12: 8. Compare FY2025 vs FY2026 segment margins and calculate change.
A13: 9. Rank geographies by revenue mix.
... A24: 20. Produce a final executive summary table using SQL CTEs.

Sheet 10_DASHBOARD_LAYOUT
A1: Dashboard Blueprint
A2: Recommended executive dashboard pages, visuals and recruiter signals.
A4: Page | B4: Dashboard Name | C4: Visuals / KPIs | D4: Recruiter Signal
A5: Page 1 | B5: Executive Overview | C5: Revenue, EBIT, PAT, margins, growth, headline KPI cards | D5: Recruiter sees business understanding first
A6: Page 2 | B6: Industry Performance | C6: Revenue by industry, YoY growth, segment margin, growth-vs-margin matrix | D6: Shows analytical diagnosis
A7: Page 3 | B7: Geography | C7: Revenue mix, top regions, concentration | D7: Shows segmentation skills
A8: Page 4 | B8: AI Transformation | C8: AI revenue, AI talent, learning, competencies, ecosystem | D8: Shows technology/business linkage
A9: Page 5 | B9: Management Insights | C9: 15 insights, risks, opportunities, recommended actions | D9: Shows communication and decision support

Sheet 11_METHODOLOGY
A1: Methodology & Sources
A2: Scope, reporting period, calculations and analytical limitations.
A4: 0 | B4: 1
A5: Source | B5: TCS Integrated Annual Report 2025-26 (FY2026), supplied PDF
A6: Reporting period | B6: April 1, 2025 – March 31, 2026
A7: Data type | B7: Publicly reported company-level data
A8: Confidential data | B8: Not used
A9: Financial units | B9: ₹ crore for INR financial statements; US$ billion where the report states USD
A10: Important limitation | B10: The report does not provide project-level client transactions, internal costs, employee-level records or confidential operational data.
A11: Recommended stack | B11: Excel → SQL → Power BI → Portfolio presentation
